LICENSE
MANIFEST.in
README.md
pyproject.toml
setup.cfg
setup.py
coffee/__init__.py
coffee/apps.py
coffee/exceptions.py
coffee/urls.py
coffee/views.py
coffee/contrib/__init__.py
coffee/contrib/decorators.py
coffee/contrib/helpers.py
coffee/contrib/parse/__init__.py
coffee/contrib/parse/functions.py
coffee/contrib/render/__init__.py
coffee/contrib/render/components.py
coffee/contrib/render/definitions.py
coffee/contrib/render/functions.py
coffee/contrib/typescript/__init__.py
coffee/contrib/typescript/functions.py
coffee/management/__init__.py
coffee/management/commands/__init__.py
coffee/management/commands/create_typescript_interfaces.py
django_coffee_tools.egg-info/PKG-INFO
django_coffee_tools.egg-info/SOURCES.txt
django_coffee_tools.egg-info/dependency_links.txt
django_coffee_tools.egg-info/requires.txt
django_coffee_tools.egg-info/top_level.txt
tests/__init__.py
tests/conftest.py
tests/models.py
tests/test_views.py