Metadata-Version: 2.1
Name: django-coffee-tools
Version: 0.1.13
Summary: A ready-to-use Django plugin which provides dynamic form generation for your Django models. These forms are intended to be integrated with your admin or management dashboard to allow easy management of your data.
Home-page: https://github.com/marzukia/coffee
Author: Andryo Marzuki
Author-email: andryo@mrzk.io
License: BSD-3-Clause
Platform: UNKNOWN
Classifier: Environment :: Web Environment
Classifier: Framework :: Django
Classifier: Framework :: Django :: 4.0
Classifier: Intended Audience :: Developers
Classifier: License :: OSI Approved :: BSD License
Classifier: Operating System :: OS Independent
Classifier: Programming Language :: Python
Classifier: Programming Language :: Python :: 3
Classifier: Programming Language :: Python :: 3 :: Only
Classifier: Programming Language :: Python :: 3.8
Classifier: Programming Language :: Python :: 3.9
Classifier: Topic :: Internet :: WWW/HTTP
Classifier: Topic :: Internet :: WWW/HTTP :: Dynamic Content
Requires-Python: >=3.6
License-File: LICENSE
